{"watchingFolders":["/home/tomii/Downloads","/home/tomii/Desktop"],"destinationFolders":{"/home/tomii/Documents":{"names":[],"formats":["txt","docx","pdf","pptx"],"regexs":[]},"/home/tomii/Music":{"names":[],"formats":["mp3"],"regexs":[]},"/home/tomii/Videos":{"names":[],"formats":["mp4","wav"],"regexs":[]},"/home/tomii/Pictures":{"names":[],"formats":["png","jpeg"],"regexs":[]}},"availableLanguages":["en-US"],"default_configurations":{"folderRecursion":0,"fileAlreadyExists":0},"warning_notifications":"enabled","last_moved":{"path":"","date":""}}